mita_client/__init__.py
mita_client/_version.py
mita_client/api.py
mita_client/client.py
mita_client/component.py
mita_client/error.py
mita_client/mita_tqdm.py
mita_client/version.txt
mita_client/view.py
mita_client-0.0.7.dist-info/LICENSE
mita_client-0.0.7.dist-info/METADATA
mita_client-0.0.7.dist-info/WHEEL
mita_client-0.0.7.dist-info/top_level.txt
mita_client-0.0.7.dist-info/RECORD
