Metadata-Version: 2.1
Name: mita_client
Version: 0.0.7
Summary: Mita client for Python.
Home-page: https://github.com/ControlNet/mita
Author: ControlNet
Author-email: smczx@hotmail.com
Project-URL: Bug Tracker, https://github.com/ControlNet/mita/issues
Project-URL: Source Code, https://github.com/ControlNet/mita
Keywords: monitoring,logging
Classifier: Programming Language :: Python :: 3
Classifier: Programming Language :: Python :: 3.7
Classifier: Programming Language :: Python :: 3.8
Classifier: Programming Language :: Python :: 3.9
Classifier: Programming Language :: Python :: 3.10
Classifier: Programming Language :: Python :: 3.11
Classifier: License :: OSI Approved :: MIT License
Classifier: Operating System :: OS Independent
Classifier: Intended Audience :: Developers
Classifier: Topic :: System :: Monitoring
Classifier: Topic :: System :: Logging
Requires-Python: >=3.6
License-File: LICENSE
